glotaran/__init__.py
glotaran/analysis/__init__.py
glotaran/builtin/__init__.py
glotaran/builtin/io/__init__.py
glotaran/builtin/io/ascii/__init__.py
glotaran/builtin/io/ascii/wavelength_time_explicit_file.py
glotaran/builtin/io/ascii/test/__init__.py
glotaran/builtin/io/ascii/test/test_explicit_file_reader.py
glotaran/builtin/io/folder/__init__.py
glotaran/builtin/io/folder/folder_plugin.py
glotaran/builtin/io/netCDF/__init__.py
glotaran/builtin/io/netCDF/netCDF.py
glotaran/builtin/io/pandas/__init__.py
glotaran/builtin/io/pandas/csv.py
glotaran/builtin/io/pandas/tsv.py
glotaran/builtin/io/pandas/xlsx.py
glotaran/builtin/io/sdt/__init__.py
glotaran/builtin/io/sdt/sdt_file_reader.py
glotaran/builtin/io/sdt/test/__init__.py
glotaran/builtin/io/sdt/test/test_file_readers.py
glotaran/builtin/io/yml/__init__.py
glotaran/builtin/io/yml/utils.py
glotaran/builtin/io/yml/yml.py
glotaran/builtin/io/yml/test/__init__.py
glotaran/builtin/io/yml/test/test_load_parameters.py
glotaran/builtin/io/yml/test/test_model_parser.py
glotaran/builtin/io/yml/test/test_save_model.py
glotaran/builtin/io/yml/test/test_save_result.py
glotaran/builtin/io/yml/test/test_save_scheme.py
glotaran/builtin/megacomplexes/__init__.py
glotaran/builtin/megacomplexes/baseline/__init__.py
glotaran/builtin/megacomplexes/baseline/baseline_megacomplex.py
glotaran/builtin/megacomplexes/clp_guide/__init__.py
glotaran/builtin/megacomplexes/clp_guide/clp_guide_megacomplex.py
glotaran/builtin/megacomplexes/coherent_artifact/__init__.py
glotaran/builtin/megacomplexes/coherent_artifact/coherent_artifact_megacomplex.py
glotaran/builtin/megacomplexes/damped_oscillation/__init__.py
glotaran/builtin/megacomplexes/damped_oscillation/damped_oscillation_megacomplex.py
glotaran/builtin/megacomplexes/decay/__init__.py
glotaran/builtin/megacomplexes/decay/decay_matrix_gaussian_irf.py
glotaran/builtin/megacomplexes/decay/decay_megacomplex.py
glotaran/builtin/megacomplexes/decay/decay_parallel_megacomplex.py
pyglotaran-0.7.4.dist-info/licenses/LICENSE
pyglotaran-0.7.4.dist-info/METADATA
pyglotaran-0.7.4.dist-info/WHEEL
pyglotaran-0.7.4.dist-info/entry_points.txt
pyglotaran-0.7.4.dist-info/top_level.txt
pyglotaran-0.7.4.dist-info/zip-safe
pyglotaran-0.7.4.dist-info/RECORD
