Metadata-Version: 2.4
Name: pyglotaran
Version: 0.7.4
Summary: The Glotaran fitting engine.
Home-page: https://github.com/glotaran/pyglotaran
Author: Joern Weissenborn, Joris Snellenburg, Sebastian Weigand, Ivo van Stokkum
Author-email: joern.weissenborn@gmail.com, j.snellenburg@gmail.com, s.weigand.phy@gmail.com, i.h.m.van.stokkum@vu.nl
License: LGPL-3.0
Project-URL: Glotaran Ecosystem, https://glotaran.org
Project-URL: Documentation, https://pyglotaran.readthedocs.io
Project-URL: Changelog, https://pyglotaran.readthedocs.io/en/latest/changelog.html
Project-URL: Source, https://github.com/glotaran/pyglotaran
Project-URL: Tracker, https://github.com/glotaran/pyglotaran/issues
Classifier: Development Status :: 4 - Beta
Classifier: Intended Audience :: Education
Classifier: Intended Audience :: Science/Research
Classifier: License :: OSI Approved :: GNU Lesser General Public License v3 (LGPLv3)
Classifier: Natural Language :: English
Classifier: Operating System :: OS Independent
Classifier: Programming Language :: Python :: 3
Classifier: Programming Language :: Python :: 3.10
Classifier: Programming Language :: Python :: 3.11
Classifier: Programming Language :: Python :: 3.12
Classifier: Programming Language :: Python :: 3.13
Classifier: Programming Language :: Python :: 3.14
Classifier: Topic :: Scientific/Engineering
Classifier: Topic :: Scientific/Engineering :: Chemistry
Classifier: Topic :: Scientific/Engineering :: Physics
Requires-Python: <3.15,>=3.10
License-File: LICENSE
Requires-Dist: asteval!=0.9.28,>=0.9.22
Requires-Dist: attrs>=22.1.0
Requires-Dist: click>=8.1.3
Requires-Dist: netCDF4>=1.5.7
Requires-Dist: numba>=0.55.0
Requires-Dist: numpy<2.4,>=1.21.2
Requires-Dist: odfpy>=1.4.1
Requires-Dist: openpyxl>=3.0.10
Requires-Dist: pandas>=1.3.4
Requires-Dist: pydantic>=2.7.2
Requires-Dist: ruamel.yaml>=0.17.17
Requires-Dist: scipy>=1.7.2
Requires-Dist: sdtfile>=2020.8.3
Requires-Dist: tabulate>=0.8.9
Requires-Dist: xarray>=2022.3.0
Provides-Extra: extras
Requires-Dist: pyglotaran-extras>=0.5.0; extra == "extras"
Provides-Extra: full
Requires-Dist: pyglotaran[extras]; extra == "full"
Requires-Dist: pyglotaran[notebook]; extra == "full"
Provides-Extra: notebook
Requires-Dist: ipykernel>=6.23.1; extra == "notebook"
Requires-Dist: jupyterlab>=4.0.0; extra == "notebook"
Dynamic: license-file
